similarweb_scraper/__init__.py
similarweb_scraper/similarweb_scraper.py
similarweb_scraper-0.0.3.dist-info/LICENSE.txt
similarweb_scraper-0.0.3.dist-info/METADATA
similarweb_scraper-0.0.3.dist-info/WHEEL
similarweb_scraper-0.0.3.dist-info/top_level.txt
similarweb_scraper-0.0.3.dist-info/RECORD
