Metadata-Version: 2.1
Name: similarweb-scraper
Version: 0.0.3
Summary: Using proxycrawl api to scrape similarweb data
Home-page: https://github.com/wchan757/similarweb_scraper
Author: Roy Lam
Author-email: 13032765d@connect.polyu.hk
License: UNKNOWN
Platform: UNKNOWN
Classifier: Programming Language :: Python :: 3
Classifier: License :: OSI Approved :: MIT License
Classifier: Operating System :: OS Independent
Requires-Python: >=3.6
